examples/__init__.py
examples/example_interface.py
examples/instanbul_predict_ise.py
examples/lending_club_predict_dti.py
examples/lending_club_predict_loan_status.py
examples/titianic_predict_survived.py
keras_pandas/Automater.py
keras_pandas/__init__.py
keras_pandas/lib.py
keras_pandas/transformations.py
keras_pandas/data_types/Abstract.py
keras_pandas/data_types/Boolean.py
keras_pandas/data_types/Categorical.py
keras_pandas/data_types/Numerical.py
keras_pandas/data_types/Text.py
keras_pandas/data_types/TimeSeries.py
keras_pandas/data_types/__init__.py
keras_pandas-3.1.0.dist-info/METADATA
keras_pandas-3.1.0.dist-info/RECORD
keras_pandas-3.1.0.dist-info/WHEEL
keras_pandas-3.1.0.dist-info/top_level.txt
tests/__init__.py
tests/testAbstractDatatype.py
tests/testAutomater.py
tests/testBoolean.py
tests/testCategorical.py
tests/testDatatypeTemplate.py
tests/testExamples.py
tests/testLib.py
tests/testNumerical.py
tests/testText.py
tests/testTimeSeries.py
tests/testbase.py
