Metadata-Version: 2.1
Name: keras-pandas
Version: 3.1.0
Summary: Easy and rapid deep learning
Home-page: https://github.com/bjherger/keras-pandas
Author: Brendan Herger
Author-email: 13herger@gmail.com
License: MIT
Project-URL: Documentation, http://keras-pandas.readthedocs.io/en/latest/intro.html
Project-URL: Code, https://github.com/bjherger/keras-pandas
Project-URL: Issue tracker, https://github.com/bjherger/keras-pandas/issues
Project-URL: PyPi, https://pypi.org/project/keras-pandas/
Project-URL: CI/CD, https://travis-ci.org/bjherger/keras-pandas/builds
Project-URL: Author's website, https://www.hergertarian.com/
Platform: UNKNOWN
Requires-Dist: gensim (==3.6.0)
Requires-Dist: h5py (==2.8.0)
Requires-Dist: Keras (==2.2.4)
Requires-Dist: m2r (==0.2.1)
Requires-Dist: numpy (==1.15.2)
Requires-Dist: pandas (==0.23.4)
Requires-Dist: requests (==2.20.1)
Requires-Dist: scikit-learn (==0.20.0)
Requires-Dist: sklearn-pandas (==1.7.0)
Requires-Dist: tensorflow (==1.11.0)
Requires-Dist: xlrd (==1.1.0)
